api_security/__init__.py
api_security/authenticate.py
api_security/authorize.py
api_security/config.py
para_api_security-1.0.0.dist-info/METADATA
para_api_security-1.0.0.dist-info/WHEEL
para_api_security-1.0.0.dist-info/top_level.txt
para_api_security-1.0.0.dist-info/RECORD
